{
    "2024-05-03 14:42:36": [
        {
            "t1": "1714727650839",
            "t2": "1714727650955"
        },
        {
            "t1": "1714727652003",
            "t2": "1714727652161"
        },
        {
            "t1": "1714727652996",
            "t2": "1714727653073"
        },
        {
            "t1": "1714727655230",
            "t2": "1714727655341"
        },
        {
            "t1": "1714727664885",
            "t2": "1714727665017"
        },
        {
            "t1": "1714727670355",
            "t2": "1714727670467"
        },
        {
            "t1": "1714727670564",
            "t2": "1714727670610"
        },
        {
            "t1": "1714727671019",
            "t2": "1714727671073"
        },
        {
            "t1": "1714727671600",
            "t2": "1714727671656"
        },
        {
            "t1": "1714727679877",
            "t2": "1714727680007"
        },
        {
            "t1": "1714727689867",
            "t2": "1714727689941"
        },
        {
            "t1": "1714727701102",
            "t2": "1714727701163"
        },
        {
            "t1": "1714727701369",
            "t2": "1714727701455"
        },
        {
            "t1": "1714727706118",
            "t2": "1714727706159"
        },
        {
            "t1": "1714727708679",
            "t2": "1714727708751"
        },
        {
            "t1": "1714727710737",
            "t2": "1714727710816"
        },
        {
            "t1": "1714727712157",
            "t2": "1714727712342"
        },
        {
            "t1": "1714727712544",
            "t2": "1714727712623"
        },
        {
            "t1": "1714727716228",
            "t2": "1714727716253"
        },
        {
            "t1": "1714727721950",
            "t2": "1714727722078"
        },
        {
            "t1": "1714727722504",
            "t2": "1714727722537"
        },
        {
            "t1": "1714727724314",
            "t2": "1714727724383"
        },
        {
            "t1": "1714727734755",
            "t2": "1714727734842"
        },
        {
            "t1": "1714727738228",
            "t2": "1714727738340"
        },
        {
            "t1": "1714727745078",
            "t2": "1714727745187"
        },
        {
            "t1": "1714727748232",
            "t2": "1714727748297"
        },
        {
            "t1": "1714727752820",
            "t2": "1714727752973"
        },
        {
            "t1": "1714727753207",
            "t2": "1714727753323"
        },
        {
            "t1": "1714727753968",
            "t2": "1714727754076"
        },
        {
            "t1": "1714727756512",
            "t2": "1714727756683"
        },
        {
            "t1": "1714727766951",
            "t2": "1714727767025"
        },
        {
            "t1": "1714727768384",
            "t2": "1714727768432"
        },
        {
            "t1": "1714727775379",
            "t2": "1714727775426"
        },
        {
            "t1": "1714727779543",
            "t2": "1714727779659"
        },
        {
            "t1": "1714727780270",
            "t2": "1714727780342"
        },
        {
            "t1": "1714727803395",
            "t2": "1714727803474"
        },
        {
            "t1": "1714727812109",
            "t2": "1714727812296"
        },
        {
            "t1": "1714727818686",
            "t2": "1714727818739"
        },
        {
            "t1": "1714727821760",
            "t2": "1714727821799"
        },
        {
            "t1": "1714727825172",
            "t2": "1714727825223"
        },
        {
            "t1": "1714727825669",
            "t2": "1714727825716"
        },
        {
            "t1": "1714727827346",
            "t2": "1714727827479"
        },
        {
            "t1": "1714727827830",
            "t2": "1714727827895"
        },
        {
            "t1": "1714727828414",
            "t2": "1714727828500"
        },
        {
            "t1": "1714727829731",
            "t2": "1714727829767"
        },
        {
            "t1": "1714727830641",
            "t2": "1714727830676"
        },
        {
            "t1": "1714727833190",
            "t2": "1714727833309"
        },
        {
            "t1": "1714727833535",
            "t2": "1714727833652"
        },
        {
            "t1": "1714727836413",
            "t2": "1714727836606"
        },
        {
            "t1": "1714727839540",
            "t2": "1714727839591"
        },
        {
            "t1": "1714727839761",
            "t2": "1714727839834"
        },
        {
            "t1": "1714727839973",
            "t2": "1714727840014"
        },
        {
            "t1": "1714727843596",
            "t2": "1714727843741"
        },
        {
            "t1": "1714727844938",
            "t2": "1714727845004"
        },
        {
            "t1": "1714727848457",
            "t2": "1714727848518"
        },
        {
            "t1": "1714727848825",
            "t2": "1714727848922"
        },
        {
            "t1": "1714727857275",
            "t2": "1714727857324"
        },
        {
            "t1": "1714727859384",
            "t2": "1714727859456"
        },
        {
            "t1": "1714727861097",
            "t2": "1714727861169"
        },
        {
            "t1": "1714727864626",
            "t2": "1714727864707"
        },
        {
            "t1": "1714727869187",
            "t2": "1714727869333"
        },
        {
            "t1": "1714727869710",
            "t2": "1714727869864"
        },
        {
            "t1": "1714727872315",
            "t2": "1714727872439"
        },
        {
            "t1": "1714727873842",
            "t2": "1714727873878"
        },
        {
            "t1": "1714727875766",
            "t2": "1714727875905"
        },
        {
            "t1": "1714727876485",
            "t2": "1714727876561"
        },
        {
            "t1": "1714727878037",
            "t2": "1714727878085"
        },
        {
            "t1": "1714727878602",
            "t2": "1714727878673"
        },
        {
            "t1": "1714727879266",
            "t2": "1714727879339"
        },
        {
            "t1": "1714727881151",
            "t2": "1714727881253"
        },
        {
            "t1": "1714727881780",
            "t2": "1714727881846"
        },
        {
            "t1": "1714727884296",
            "t2": "1714727884409"
        },
        {
            "t1": "1714727885980",
            "t2": "1714727886057"
        },
        {
            "t1": "1714727888917",
            "t2": "1714727888969"
        },
        {
            "t1": "1714727896453",
            "t2": "1714727896504"
        },
        {
            "t1": "1714727896453",
            "t2": "1714727898761"
        }
    ],
    "Prompt1": [
        {
            "P1": "1714727663576"
        },
        {
            "P1": "1714727679740"
        },
        {
            "P1": "1714727688014"
        },
        {
            "P1": "1714727693958"
        },
        {
            "P1": "1714727697969"
        },
        {
            "P1": "1714727732506"
        },
        {
            "P1": "1714727764810"
        },
        {
            "P1": "1714727788344"
        },
        {
            "P1": "1714727796367"
        },
        {
            "P1": "1714727807517"
        },
        {
            "P1": "1714727811531"
        },
        {
            "P1": "1714727816327"
        },
        {
            "P1": "1714727857160"
        }
    ],
    "2024-05-03 16:25:32": [
        {
            "t1": "1714733735053",
            "t2": "1714733735640"
        }
    ]
}