{
    "2024-05-01 12:35:45": [
        {
            "t1": "1714547493481",
            "t2": "1714547493579"
        },
        {
            "t1": "1714547494253",
            "t2": "1714547494285"
        },
        {
            "t1": "1714547495092",
            "t2": "1714547495152"
        },
        {
            "t1": "1714547495606",
            "t2": "1714547495649"
        },
        {
            "t1": "1714547497146",
            "t2": "1714547497227"
        },
        {
            "t1": "1714547497146",
            "t2": "1714547497546"
        }
    ],
    "2024-05-01 13:17:48": [
        {
            "t1": "1714549676166",
            "t2": "1714549676312"
        }
    ],
    "2024-05-01 13:19:45": [
        {
            "t1": "1714549785493",
            "t2": "1714549785621"
        }
    ]
}