{
    "2024-05-10 14:26:26": [
        {
            "t1": "1715331642612",
            "t2": "1715331642787"
        },
        {
            "t1": "1715331644805",
            "t2": "1715331645059"
        },
        {
            "t1": "1715331646488",
            "t2": "1715331646646"
        },
        {
            "t1": "1715331647858",
            "t2": "1715331648162"
        },
        {
            "t1": "1715331650055",
            "t2": "1715331650226"
        },
        {
            "t1": "1715331650994",
            "t2": "1715331652130"
        },
        {
            "t1": "1715331652243",
            "t2": "1715331652292"
        },
        {
            "t1": "1715331652243",
            "t2": "1715331653526"
        }
    ]
}