{
    "2024-05-06 13:20:47": [
        {
            "t1": "1714981852296",
            "t2": "1714981852486"
        },
        {
            "t1": "1714981857884",
            "t2": "1714981858011"
        },
        {
            "t1": "1714981859124",
            "t2": "1714981859378"
        },
        {
            "t1": "1714981861434",
            "t2": "1714981861624"
        },
        {
            "t1": "1714981862933",
            "t2": "1714981863040"
        },
        {
            "t1": "1714981864757",
            "t2": "1714981865155"
        },
        {
            "t1": "1714981866867",
            "t2": "1714981867283"
        },
        {
            "t1": "1714981867946",
            "t2": "1714981868334"
        },
        {
            "t1": "1714981868979",
            "t2": "1714981869197"
        },
        {
            "t1": "1714981871199",
            "t2": "1714981871387"
        },
        {
            "t1": "1714981872742",
            "t2": "1714981873117"
        },
        {
            "t1": "1714981875270",
            "t2": "1714981875463"
        },
        {
            "t1": "1714981878319",
            "t2": "1714981878584"
        },
        {
            "t1": "1714981881111",
            "t2": "1714981881262"
        },
        {
            "t1": "1714981884833",
            "t2": "1714981885080"
        },
        {
            "t1": "1714981886668",
            "t2": "1714981886823"
        },
        {
            "t1": "1714981889355",
            "t2": "1714981889599"
        },
        {
            "t1": "1714981890946",
            "t2": "1714981891146"
        },
        {
            "t1": "1714981893378",
            "t2": "1714981893624"
        },
        {
            "t1": "1714981893378",
            "t2": "1714981895412"
        }
    ],
    "2024-05-06 13:24:01": [
        {
            "t1": "1714982045209",
            "t2": "1714982045440"
        }
    ],
    "2024-05-06 13:29:58": [
        {
            "t1": "1714982400908",
            "t2": "1714982401321"
        }
    ],
    "2024-05-06 14:17:20": [
        {
            "t1": "1714985242561",
            "t2": "1714985261934"
        }
    ],
    "2024-05-06 14:43:56": [
        {
            "t1": "1714986835833",
            "t2": "1714986836403"
        }
    ],
    "2024-05-06 14:46:47": [
        {
            "t1": "1714987009340",
            "t2": "1714987009390"
        }
    ],
    "2024-05-06 15:11:06": [
        {
            "t1": "1714988454191",
            "t2": "1714988467246"
        }
    ]
}