{
    "2024-04-25 21:03:47": [
        {
            "t1": "1714059230999",
            "t2": "1714059231220"
        },
        {
            "t1": "1714059232135",
            "t2": "1714059232350"
        },
        {
            "t1": "1714059233198",
            "t2": "1714059233368"
        },
        {
            "t1": "1714059234666",
            "t2": "1714059234820"
        },
        {
            "t1": "1714059235403",
            "t2": "1714059235560"
        },
        {
            "t1": "1714059237279",
            "t2": "1714059237491"
        },
        {
            "t1": "1714059238937",
            "t2": "1714059239095"
        },
        {
            "t1": "1714059239741",
            "t2": "1714059239883"
        },
        {
            "t1": "1714059241744",
            "t2": "1714059241823"
        },
        {
            "t1": "1714059242278",
            "t2": "1714059242429"
        },
        {
            "t1": "1714059245941",
            "t2": "1714059246130"
        },
        {
            "t1": "1714059246996",
            "t2": "1714059247162"
        },
        {
            "t1": "1714059249075",
            "t2": "1714059249162"
        },
        {
            "t1": "1714059249075",
            "t2": "1714059250051"
        }
    ]
}