{
    "2024-05-02 12:35:23": [
        {
            "t1": "1714633576036",
            "t2": "1714633576745"
        },
        {
            "t1": "1714633579558",
            "t2": "1714633580682"
        },
        {
            "t1": "1714633606164",
            "t2": "1714633606230"
        },
        {
            "t1": "1714633606893",
            "t2": "1714633607095"
        },
        {
            "t1": "1714633617648",
            "t2": "1714633617765"
        },
        {
            "t1": "1714633639896",
            "t2": "1714633639964"
        },
        {
            "t1": "1714633639896",
            "t2": "1714633643499"
        }
    ],
    "Prompt1": [
        {
            "P1": "1714633588686"
        },
        {
            "P1": "1714633596691"
        },
        {
            "P1": "1714633604692"
        },
        {
            "P1": "1714633611147"
        },
        {
            "P1": "1714633615157"
        },
        {
            "P1": "1714633625769"
        },
        {
            "P1": "1714633633821"
        }
    ]
}