{
    "2024-04-25 11:07:27": [
        {
            "t1": "1714023447694",
            "t2": "1714023447816"
        },
        {
            "t1": "1714023448318",
            "t2": "1714023448769"
        },
        {
            "t1": "1714023450337",
            "t2": "1714023450438"
        },
        {
            "t1": "1714023451325",
            "t2": "1714023451490"
        },
        {
            "t1": "1714023463574",
            "t2": "1714023463915"
        },
        {
            "t1": "1714023466525",
            "t2": "1714023467853"
        },
        {
            "t1": "1714023466525",
            "t2": "1714023473064"
        }
    ],
    "Prompt1": [
        {
            "P1": "1714023459577"
        }
    ]
}