{
    "2024-05-03 16:26:47": [
        {
            "t1": "1714733808034",
            "t2": "1714733808092"
        },
        {
            "t1": "1714733808464",
            "t2": "1714733808893"
        },
        {
            "t1": "1714733809126",
            "t2": "1714733809242"
        },
        {
            "t1": "1714733810835",
            "t2": "1714733811019"
        },
        {
            "t1": "1714733811097",
            "t2": "1714733811142"
        },
        {
            "t1": "1714733811508",
            "t2": "1714733811605"
        },
        {
            "t1": "1714733811802",
            "t2": "1714733811856"
        },
        {
            "t1": "1714733812148",
            "t2": "1714733812313"
        },
        {
            "t1": "1714733812868",
            "t2": "1714733812951"
        },
        {
            "t1": "1714733813446",
            "t2": "1714733813509"
        },
        {
            "t1": "1714733813974",
            "t2": "1714733814226"
        },
        {
            "t1": "1714733814508",
            "t2": "1714733814739"
        },
        {
            "t1": "1714733815339",
            "t2": "1714733815395"
        },
        {
            "t1": "1714733817217",
            "t2": "1714733817360"
        },
        {
            "t1": "1714733817636",
            "t2": "1714733817690"
        },
        {
            "t1": "1714733817785",
            "t2": "1714733817840"
        },
        {
            "t1": "1714733818102",
            "t2": "1714733818173"
        },
        {
            "t1": "1714733818295",
            "t2": "1714733818363"
        },
        {
            "t1": "1714733818711",
            "t2": "1714733818784"
        },
        {
            "t1": "1714733819161",
            "t2": "1714733819234"
        },
        {
            "t1": "1714733819356",
            "t2": "1714733819420"
        },
        {
            "t1": "1714733820149",
            "t2": "1714733820360"
        },
        {
            "t1": "1714733821834",
            "t2": "1714733821902"
        },
        {
            "t1": "1714733822117",
            "t2": "1714733822288"
        },
        {
            "t1": "1714733822796",
            "t2": "1714733822978"
        },
        {
            "t1": "1714733823468",
            "t2": "1714733823533"
        },
        {
            "t1": "1714733823965",
            "t2": "1714733824090"
        },
        {
            "t1": "1714733824406",
            "t2": "1714733824471"
        },
        {
            "t1": "1714733824951",
            "t2": "1714733825049"
        },
        {
            "t1": "1714733825964",
            "t2": "1714733826061"
        },
        {
            "t1": "1714733826511",
            "t2": "1714733826609"
        },
        {
            "t1": "1714733826848",
            "t2": "1714733826893"
        },
        {
            "t1": "1714733826848",
            "t2": "1714733827757"
        }
    ]
}