{
    "2024-05-02 13:58:09": [
        {
            "t1": "1714638912075",
            "t2": "1714638912338"
        },
        {
            "t1": "1714638912534",
            "t2": "1714638912612"
        },
        {
            "t1": "1714638913336",
            "t2": "1714638913454"
        },
        {
            "t1": "1714638913968",
            "t2": "1714638914078"
        },
        {
            "t1": "1714638914568",
            "t2": "1714638914810"
        },
        {
            "t1": "1714638915353",
            "t2": "1714638915567"
        },
        {
            "t1": "1714638916769",
            "t2": "1714638916927"
        },
        {
            "t1": "1714638917447",
            "t2": "1714638917859"
        },
        {
            "t1": "1714638918238",
            "t2": "1714638918383"
        },
        {
            "t1": "1714638920522",
            "t2": "1714638920696"
        },
        {
            "t1": "1714638922850",
            "t2": "1714638923009"
        },
        {
            "t1": "1714638925543",
            "t2": "1714638925623"
        },
        {
            "t1": "1714638930192",
            "t2": "1714638930363"
        },
        {
            "t1": "1714638930954",
            "t2": "1714638931171"
        },
        {
            "t1": "1714638936084",
            "t2": "1714638936228"
        },
        {
            "t1": "1714638938922",
            "t2": "1714638939124"
        },
        {
            "t1": "1714638942264",
            "t2": "1714638942421"
        },
        {
            "t1": "1714638943281",
            "t2": "1714638943364"
        },
        {
            "t1": "1714638943598",
            "t2": "1714638943666"
        },
        {
            "t1": "1714638944151",
            "t2": "1714638944230"
        },
        {
            "t1": "1714638947231",
            "t2": "1714638947360"
        },
        {
            "t1": "1714638948024",
            "t2": "1714638948262"
        },
        {
            "t1": "1714638950014",
            "t2": "1714638950160"
        },
        {
            "t1": "1714638957728",
            "t2": "1714638957879"
        },
        {
            "t1": "1714638961978",
            "t2": "1714638962072"
        },
        {
            "t1": "1714638963972",
            "t2": "1714638964058"
        },
        {
            "t1": "1714638972183",
            "t2": "1714638972271"
        },
        {
            "t1": "1714638973398",
            "t2": "1714638973567"
        },
        {
            "t1": "1714638973677",
            "t2": "1714638973808"
        },
        {
            "t1": "1714638974841",
            "t2": "1714638975030"
        },
        {
            "t1": "1714638975868",
            "t2": "1714638976077"
        },
        {
            "t1": "1714638976482",
            "t2": "1714638976706"
        },
        {
            "t1": "1714638978075",
            "t2": "1714638978193"
        },
        {
            "t1": "1714638980670",
            "t2": "1714638980755"
        },
        {
            "t1": "1714638985087",
            "t2": "1714638985197"
        },
        {
            "t1": "1714638988801",
            "t2": "1714638988923"
        },
        {
            "t1": "1714638990657",
            "t2": "1714638990729"
        },
        {
            "t1": "1714638994985",
            "t2": "1714638995145"
        },
        {
            "t1": "1714638996540",
            "t2": "1714638996662"
        },
        {
            "t1": "1714638999607",
            "t2": "1714638999737"
        },
        {
            "t1": "1714639002474",
            "t2": "1714639002597"
        },
        {
            "t1": "1714639003697",
            "t2": "1714639003850"
        },
        {
            "t1": "1714639004441",
            "t2": "1714639004691"
        },
        {
            "t1": "1714639006926",
            "t2": "1714639007074"
        },
        {
            "t1": "1714639007338",
            "t2": "1714639007431"
        },
        {
            "t1": "1714639008033",
            "t2": "1714639008116"
        },
        {
            "t1": "1714639008326",
            "t2": "1714639008474"
        },
        {
            "t1": "1714639008621",
            "t2": "1714639008758"
        }
    ],
    "Prompt1": [
        {
            "P1": "1714638972077"
        }
    ],
    "2024-05-02 14:46:52": [
        {
            "t1": "1714641412856",
            "t2": "1714641413035"
        }
    ]
}