{
    "2024-05-08 15:57:53": [
        {
            "t1": "1715164586526",
            "t2": "1715164586703"
        },
        {
            "t1": "1715164586990",
            "t2": "1715164587148"
        },
        {
            "t1": "1715164593613",
            "t2": "1715164593692"
        },
        {
            "t1": "1715164596253",
            "t2": "1715164596336"
        },
        {
            "t1": "1715164598894",
            "t2": "1715164599081"
        },
        {
            "t1": "1715164599676",
            "t2": "1715164600006"
        },
        {
            "t1": "1715164600252",
            "t2": "1715164600520"
        },
        {
            "t1": "1715164603327",
            "t2": "1715164603469"
        },
        {
            "t1": "1715164614637",
            "t2": "1715164614848"
        },
        {
            "t1": "1715164615037",
            "t2": "1715164615095"
        },
        {
            "t1": "1715164615438",
            "t2": "1715164615592"
        },
        {
            "t1": "1715164616325",
            "t2": "1715164616423"
        },
        {
            "t1": "1715164617983",
            "t2": "1715164618188"
        },
        {
            "t1": "1715164620460",
            "t2": "1715164620510"
        },
        {
            "t1": "1715164621090",
            "t2": "1715164621342"
        },
        {
            "t1": "1715164621518",
            "t2": "1715164621672"
        },
        {
            "t1": "1715164624894",
            "t2": "1715164625048"
        },
        {
            "t1": "1715164625820",
            "t2": "1715164625915"
        },
        {
            "t1": "1715164630638",
            "t2": "1715164630747"
        },
        {
            "t1": "1715164630865",
            "t2": "1715164630923"
        },
        {
            "t1": "1715164632907",
            "t2": "1715164633036"
        },
        {
            "t1": "1715164636541",
            "t2": "1715164636709"
        },
        {
            "t1": "1715164639054",
            "t2": "1715164639149"
        },
        {
            "t1": "1715164639310",
            "t2": "1715164639446"
        },
        {
            "t1": "1715164646293",
            "t2": "1715164646473"
        },
        {
            "t1": "1715164649086",
            "t2": "1715164649164"
        },
        {
            "t1": "1715164678499",
            "t2": "1715164678623"
        },
        {
            "t1": "1715164681257",
            "t2": "1715164681434"
        },
        {
            "t1": "1715164689024",
            "t2": "1715164689068"
        },
        {
            "t1": "1715164689297",
            "t2": "1715164689391"
        },
        {
            "t1": "1715164706894",
            "t2": "1715164707289"
        },
        {
            "t1": "1715164710541",
            "t2": "1715164710707"
        },
        {
            "t1": "1715164712464",
            "t2": "1715164712713"
        },
        {
            "t1": "1715164725005",
            "t2": "1715164725120"
        },
        {
            "t1": "1715164725245",
            "t2": "1715164725309"
        },
        {
            "t1": "1715164730243",
            "t2": "1715164730315"
        },
        {
            "t1": "1715164731275",
            "t2": "1715164731499"
        },
        {
            "t1": "1715164732028",
            "t2": "1715164732183"
        },
        {
            "t1": "1715164733199",
            "t2": "1715164733371"
        },
        {
            "t1": "1715164733792",
            "t2": "1715164733931"
        },
        {
            "t1": "1715164736347",
            "t2": "1715164736637"
        },
        {
            "t1": "1715164737613",
            "t2": "1715164737808"
        },
        {
            "t1": "1715164750621",
            "t2": "1715164750796"
        },
        {
            "t1": "1715164751457",
            "t2": "1715164751499"
        },
        {
            "t1": "1715164751803",
            "t2": "1715164751939"
        },
        {
            "t1": "1715164752159",
            "t2": "1715164752381"
        },
        {
            "t1": "1715164758635",
            "t2": "1715164758762"
        },
        {
            "t1": "1715164764551",
            "t2": "1715164764648"
        },
        {
            "t1": "1715164764831",
            "t2": "1715164764935"
        },
        {
            "t1": "1715164765727",
            "t2": "1715164765998"
        },
        {
            "t1": "1715164766110",
            "t2": "1715164766382"
        },
        {
            "t1": "1715164782995",
            "t2": "1715164783101"
        },
        {
            "t1": "1715164798752",
            "t2": "1715164798948"
        },
        {
            "t1": "1715164809630",
            "t2": "1715164809855"
        },
        {
            "t1": "1715164818324",
            "t2": "1715164818416"
        },
        {
            "t1": "1715164818824",
            "t2": "1715164818871"
        },
        {
            "t1": "1715164819080",
            "t2": "1715164819194"
        },
        {
            "t1": "1715164840268",
            "t2": "1715164840425"
        },
        {
            "t1": "1715164844120",
            "t2": "1715164844343"
        },
        {
            "t1": "1715164847661",
            "t2": "1715164847787"
        },
        {
            "t1": "1715164847963",
            "t2": "1715164848071"
        },
        {
            "t1": "1715164848270",
            "t2": "1715164848348"
        },
        {
            "t1": "1715164848924",
            "t2": "1715164849037"
        },
        {
            "t1": "1715164849178",
            "t2": "1715164849294"
        },
        {
            "t1": "1715164858253",
            "t2": "1715164858505"
        }
    ],
    "Prompt1": [
        {
            "P1": "1715164611660"
        },
        {
            "P1": "1715164657212"
        },
        {
            "P1": "1715164665221"
        },
        {
            "P1": "1715164673234"
        },
        {
            "P1": "1715164685466"
        },
        {
            "P1": "1715164697406"
        },
        {
            "P1": "1715164705420"
        },
        {
            "P1": "1715164720747"
        },
        {
            "P1": "1715164745995"
        },
        {
            "P1": "1715164774560"
        },
        {
            "P1": "1715164782586"
        },
        {
            "P1": "1715164787116"
        },
        {
            "P1": "1715164791135"
        },
        {
            "P1": "1715164795168"
        },
        {
            "P1": "1715164802986"
        },
        {
            "P1": "1715164807020"
        },
        {
            "P1": "1715164813876"
        },
        {
            "P1": "1715164817906"
        },
        {
            "P1": "1715164827298"
        },
        {
            "P1": "1715164835312"
        },
        {
            "P1": "1715164857422"
        }
    ]
}