{
    "2024-05-11 11:09:07": [
        {
            "t1": "1715406027454",
            "t2": "1715406027657"
        },
        {
            "t1": "1715406027929",
            "t2": "1715406028041"
        },
        {
            "t1": "1715406031262",
            "t2": "1715406031400"
        },
        {
            "t1": "1715406034105",
            "t2": "1715406034250"
        },
        {
            "t1": "1715406034746",
            "t2": "1715406034890"
        },
        {
            "t1": "1715406040235",
            "t2": "1715406040377"
        },
        {
            "t1": "1715406041224",
            "t2": "1715406041377"
        },
        {
            "t1": "1715406042527",
            "t2": "1715406042784"
        },
        {
            "t1": "1715406042527",
            "t2": "1715406043568"
        }
    ],
    "2024-05-11 11:13:53": [
        {
            "t1": "1715406321148",
            "t2": "1715406321233"
        }
    ],
    "2024-05-11 11:45:39": [
        {
            "t1": "1715408162462",
            "t2": "1715408162548"
        }
    ],
    "2024-05-11 14:10:22": [
        {
            "t1": "1715416843006",
            "t2": "1715416843143"
        }
    ],
    "Prompt1": [
        {
            "P1": "1715417220208"
        },
        {
            "P1": "1715418462270"
        }
    ],
    "2024-05-11 14:37:23": [
        {
            "t1": "1715418454207",
            "t2": "1715418454263"
        }
    ],
    "2024-05-11 15:42:20": [
        {
            "t1": "1715422429878",
            "t2": "1715422430054"
        }
    ]
}