{
    "2024-05-03 18:09:04": [
        {
            "t1": "1714740319995",
            "t2": "1714740320043"
        },
        {
            "t1": "1714740320733",
            "t2": "1714740320923"
        },
        {
            "t1": "1714740321455",
            "t2": "1714740321567"
        },
        {
            "t1": "1714740322923",
            "t2": "1714740322995"
        },
        {
            "t1": "1714740325252",
            "t2": "1714740325314"
        },
        {
            "t1": "1714740330378",
            "t2": "1714740330451"
        },
        {
            "t1": "1714740333654",
            "t2": "1714740333848"
        },
        {
            "t1": "1714740334616",
            "t2": "1714740335098"
        },
        {
            "t1": "1714740339226",
            "t2": "1714740339283"
        },
        {
            "t1": "1714740340346",
            "t2": "1714740340406"
        },
        {
            "t1": "1714740342147",
            "t2": "1714740342338"
        },
        {
            "t1": "1714740345083",
            "t2": "1714740345138"
        },
        {
            "t1": "1714740345083",
            "t2": "1714740349770"
        }
    ]
}