{
    "2024-05-10 12:16:03": [
        {
            "t1": "1715323575764",
            "t2": "1715323575812"
        },
        {
            "t1": "1715323575948",
            "t2": "1715323576069"
        },
        {
            "t1": "1715323576459",
            "t2": "1715323576627"
        },
        {
            "t1": "1715323576721",
            "t2": "1715323576796"
        },
        {
            "t1": "1715323577121",
            "t2": "1715323577235"
        },
        {
            "t1": "1715323577715",
            "t2": "1715323577907"
        },
        {
            "t1": "1715323580100",
            "t2": "1715323580578"
        },
        {
            "t1": "1715323581122",
            "t2": "1715323581176"
        },
        {
            "t1": "1715323582740",
            "t2": "1715323582995"
        },
        {
            "t1": "1715323583367",
            "t2": "1715323583511"
        },
        {
            "t1": "1715323592274",
            "t2": "1715323592452"
        },
        {
            "t1": "1715323592852",
            "t2": "1715323593075"
        },
        {
            "t1": "1715323594325",
            "t2": "1715323594419"
        },
        {
            "t1": "1715323595729",
            "t2": "1715323595875"
        },
        {
            "t1": "1715323596071",
            "t2": "1715323596161"
        },
        {
            "t1": "1715323596457",
            "t2": "1715323596604"
        },
        {
            "t1": "1715323598002",
            "t2": "1715323598131"
        },
        {
            "t1": "1715323598306",
            "t2": "1715323598450"
        },
        {
            "t1": "1715323599786",
            "t2": "1715323599836"
        },
        {
            "t1": "1715323600578",
            "t2": "1715323600709"
        },
        {
            "t1": "1715323600821",
            "t2": "1715323600933"
        },
        {
            "t1": "1715323601027",
            "t2": "1715323601132"
        },
        {
            "t1": "1715323603514",
            "t2": "1715323603749"
        },
        {
            "t1": "1715323603514",
            "t2": "1715323605251"
        }
    ],
    "Prompt1": [
        {
            "P1": "1715323591717"
        },
        {
            "P1": "1715337403546"
        }
    ],
    "2024-05-10 12:27:13": [
        {
            "t1": "1715324239541",
            "t2": "1715324239649"
        }
    ],
    "2024-05-10 18:22:28": [
        {
            "t1": "1715345598460",
            "t2": "1715345598508"
        }
    ]
}