{
    "2024-05-03 11:59:30": [
        {
            "t1": "1714717770913",
            "t2": "1714717770982"
        },
        {
            "t1": "1714717770913",
            "t2": "1714717771549"
        }
    ],
    "2024-05-03 12:16:00": [
        {
            "t1": "1714718805549",
            "t2": "1714718805729"
        }
    ],
    "2024-05-03 12:29:38": [
        {
            "t1": "1714719587913",
            "t2": "1714719589128"
        }
    ],
    "2024-05-03 14:34:09": [
        {
            "t1": "1714727049035",
            "t2": "1714727489402"
        }
    ],
    "2024-05-03 16:18:36": [
        {
            "t1": "1714733317632",
            "t2": "1714733317719"
        }
    ]
}