{
    "2024-04-25 23:22:43": [
        {
            "t1": "1714067702989",
            "t2": "1714067703099"
        },
        {
            "t1": "1714067704608",
            "t2": "1714067704781"
        },
        {
            "t1": "1714067707963",
            "t2": "1714067708172"
        },
        {
            "t1": "1714067710384",
            "t2": "1714067710598"
        },
        {
            "t1": "1714067713585",
            "t2": "1714067713757"
        },
        {
            "t1": "1714067714324",
            "t2": "1714067714487"
        },
        {
            "t1": "1714067715015",
            "t2": "1714067715125"
        },
        {
            "t1": "1714067715597",
            "t2": "1714067715813"
        },
        {
            "t1": "1714067717348",
            "t2": "1714067717494"
        },
        {
            "t1": "1714067724211",
            "t2": "1714067724290"
        },
        {
            "t1": "1714067727568",
            "t2": "1714067727678"
        },
        {
            "t1": "1714067728858",
            "t2": "1714067729033"
        },
        {
            "t1": "1714067731535",
            "t2": "1714067731634"
        },
        {
            "t1": "1714067733724",
            "t2": "1714067733935"
        },
        {
            "t1": "1714067734967",
            "t2": "1714067735108"
        },
        {
            "t1": "1714067741505",
            "t2": "1714067741615"
        },
        {
            "t1": "1714067743501",
            "t2": "1714067743689"
        },
        {
            "t1": "1714067751307",
            "t2": "1714067751496"
        },
        {
            "t1": "1714067759303",
            "t2": "1714067759460"
        },
        {
            "t1": "1714067762895",
            "t2": "1714067763037"
        },
        {
            "t1": "1714067767472",
            "t2": "1714067767620"
        },
        {
            "t1": "1714067771012",
            "t2": "1714067771262"
        },
        {
            "t1": "1714067776241",
            "t2": "1714067776557"
        },
        {
            "t1": "1714067781201",
            "t2": "1714067781328"
        },
        {
            "t1": "1714067789046",
            "t2": "1714067789188"
        },
        {
            "t1": "1714067794445",
            "t2": "1714067794634"
        },
        {
            "t1": "1714067794759",
            "t2": "1714067794822"
        },
        {
            "t1": "1714067795703",
            "t2": "1714067795983"
        },
        {
            "t1": "1714067805169",
            "t2": "1714067805280"
        },
        {
            "t1": "1714067805996",
            "t2": "1714067806088"
        }
    ],
    "Prompt1": [
        {
            "P1": "1714067804114"
        }
    ]
}