{
    "2024-04-29 12:39:50": [
        {
            "t1": "1714374593143",
            "t2": "1714374593751"
        },
        {
            "t1": "1714374598965",
            "t2": "1714374599028"
        },
        {
            "t1": "1714374603927",
            "t2": "1714374604122"
        },
        {
            "t1": "1714374627285",
            "t2": "1714374627494"
        },
        {
            "t1": "1714374638164",
            "t2": "1714374638895"
        },
        {
            "t1": "1714374638164",
            "t2": "1714374669683"
        }
    ],
    "Prompt1": [
        {
            "P1": "1714374612161"
        },
        {
            "P1": "1714374620165"
        },
        {
            "P1": "1714374631546"
        },
        {
            "P1": "1714374635554"
        },
        {
            "P1": "1714374642956"
        },
        {
            "P1": "1714374646966"
        },
        {
            "P1": "1714374651016"
        },
        {
            "P1": "1714374655018"
        },
        {
            "P1": "1714374659019"
        },
        {
            "P1": "1714374663026"
        },
        {
            "P1": "1714374667027"
        }
    ]
}