{
    "2024-04-25 20:03:38": [
        {
            "t1": "1714056120477",
            "t2": "1714056125891"
        }
    ],
    "2024-04-25 21:01:29": [
        {
            "t1": "1714059095293",
            "t2": "1714059095498"
        },
        {
            "t1": "1714059096964",
            "t2": "1714059097106"
        },
        {
            "t1": "1714059098482",
            "t2": "1714059098640"
        },
        {
            "t1": "1714059099493",
            "t2": "1714059099697"
        },
        {
            "t1": "1714059100769",
            "t2": "1714059100975"
        },
        {
            "t1": "1714059103217",
            "t2": "1714059103296"
        },
        {
            "t1": "1714059104888",
            "t2": "1714059105022"
        },
        {
            "t1": "1714059105503",
            "t2": "1714059105692"
        },
        {
            "t1": "1714059106229",
            "t2": "1714059106424"
        },
        {
            "t1": "1714059107158",
            "t2": "1714059107296"
        },
        {
            "t1": "1714059107839",
            "t2": "1714059108026"
        },
        {
            "t1": "1714059109028",
            "t2": "1714059109557"
        },
        {
            "t1": "1714059109028",
            "t2": "1714059109778"
        }
    ],
    "2024-04-25 21:01:56": [
        {
            "t1": "1714059115858",
            "t2": "1714059117623"
        }
    ]
}